[{"id":"9a892f5a.6792c","type":"tab","label":"W&T rule.box Demo","disabled":false,"info":""},{"id":"7b8c4fe8.42cd6","type":"ui_text","z":"9a892f5a.6792c","group":"2e4f7b1f.9ea784","order":3,"width":"0","height":"0","name":"","label":"Quelle:","format":"<a href=\"http://klima.wut.de/\" target=\"_blank\">klima.wut.de</a>","layout":"row-spread","x":400,"y":160,"wires":[]},{"id":"7e596ea.108669","type":"Analog IN","z":"9a892f5a.6792c","name":"","webio":"bb4ed575.d95f18","number":1,"x":160,"y":80,"wires":[["983b6570.944988","a5544d7.17a32b"]]},{"id":"983b6570.944988","type":"ui_chart","z":"9a892f5a.6792c","name":"","group":"2e4f7b1f.9ea784","order":2,"width":0,"height":0,"label":"Temperaturverlauf","chartType":"line","legend":"false","xformat": "dd HH:mm","interpolate":"linear","nodata":"Daten werden geladen...","dot":false,"ymin":"","ymax":"","removeOlder":1,"removeOlderPoints":"","removeOlderUnit":"604800","cutout":0,"useOneColor":false,"colors":["#0094ce","#aec7e8","#ff7f0e","#2ca02c","#98df8a","#d62728","#ff9896","#9467bd","#c5b0d5"],"useOldStyle":false,"outputs":1,"x":430,"y":120,"wires":[[]]},{"id":"a5544d7.17a32b","type":"ui_gauge","z":"9a892f5a.6792c","name":"","group":"2e4f7b1f.9ea784","order":1,"width":0,"height":0,"gtype":"gage","title":"Außentemperatur","label":"°C","format":"{{value}}","min":"-10","max":"40","colors":["#00b500","#e6e600","#ca3838"],"seg1":"15","seg2":"30","x":430,"y":80,"wires":[]},{"id":"2e4f7b1f.9ea784","type":"ui_group","z":"","name":"Grüße aus Wuppertal","tab":"a61c5c26.0e87b","order":1,"disp":true,"width":"6","collapse":false},{"id":"bb4ed575.d95f18","type":"Web-IO","z":"","name":"","protocol":"http","host":"klima.wut.de","port":"80","pollingIntervalValue":10,"pollingIntervalFactor":60000,"portinfoIntervalSec":3600,"manualConfig":true,"device":null},{"id":"a61c5c26.0e87b","type":"ui_tab","z":"","name":"W&T rule.box","icon":"dashboard","disabled":false,"hidden":false}]